Workbook

Sheet Lista
B1: Mês | D1: Código Centro de Custo | E1: Centro de Custos
B2: Jan/2026 | D2: 25111001 | E2: TI - DIVISAO DE NEGOCIO
B3: Fev/2026
B4: Mar/2026
B5: Abr/2026
B6: Mai/2026
B7: Jun/2026
B8: Jul/2026
B9: Ago/2026
B10: Set/2026
B11: Out/2026
B12: Nov/2026
B13: Dez/2026

Sheet Janeiro
D1: ANÁLISE MENSAL BUDGET 2026
E4: ="Itapevi, "&TEXT(TODAY(),"dd ""de"" mmmm ""de"" aaaa")
B6: MÊS DE REFERÊNCIA | C6: Jan/2026
B7: RESPONSÁVEL | C7: Widson Rodrigues da Araujo - Gerente
B8: CENTRO DE CUSTO | C8: 25111001 - TI - DIVISAO DE NEGOCIO
G11: BUDGET/ANO | H11: 3329276.1
G13: BUDGET/MÊS | H13: 268847.77
F15: CONSUMO ACUMULADO ATÉ O MÊS ANTERIOR | H15: 0
B17: CONTA CONTÁBIL | C17: FORNECEDOR | E17: DESCRIÇÃO | F17: DATA DE EMISSÃO | G17: DATA DE ENTREGA | H17: VALOR
B19: 6.03.01.02.02.79 - ASSESSORIA OPERACIONAL | C19: CRISTIANO AGOSTINHO DA SILVA - ME | E19: ASSESSORIA OPERACIONAL / SUPORTE 1.07 | F19: 46028 | G19: 46029 | H19: 14019.64
B20: 6.03.01.02.02.79 - ASSESSORIA OPERACIONAL | C20: F.P. ROSA SERVICOS DE INFORMATICA | E20: ASSESSORIA ELABORACAO PROGRAMA 1.04 | F20: 46029 | G20: 46029 | H20: 13025
B21: 6.03.01.02.02.79 - ASSESSORIA OPERACIONAL | C21: GS SERVICOS DE INFORMATICA EIRELI - ME | E21: ASSESSORIA OPERACIONAL 17.02 | F21: 46029 | G21: 46029 | H21: 21000
B22: 6.03.01.02.02.51 - INTERNET/COMUNICACOES | C22: VOGEL SOLUCOES EM TELECOMUNICACOES E INFORMATICA S.A. | E22: SERV. LINK INTERNET 01.04 | F22: 46000 | G22: 46031 | H22: 1390.37
B23: 6.03.01.02.02.51 - INTERNET/COMUNICACOES | C23: VOGEL SOLUCOES EM TELECOMUNICACOES E INFORMATICA S.A. | E23: SERV. LINK INTERNET 01.04 | F23: 46000 | G23: 46031 | H23: 1390.37
B24: 6.03.01.02.02.51 - INTERNET/COMUNICACOES | C24: VOGEL SOLUCOES EM TELECOMUNICACOES E INFORMATICA S.A. | E24: SERV. LINK INTERNET 01.04 | F24: 46000 | G24: 46031 | H24: 1716.58
B25: 6.03.01.02.02.52 - TELEFONES | C25: TELECOMUNICACOES DE SAO PAULO S.A. -TELEFONICA | E25: SERV. TELEFONIA FIXA 31.01 | F25: 46010 | G25: 46031 | H25: 6121.87
B26: 6.03.01.02.02.52 - TELEFONES | C26: TELECOMUNICACOES DE SAO PAULO S.A. -TELEFONICA | E26: SERV. TELEFONIA FIXA 31.01 | F26: 46010 | G26: 46031 | H26: 4468.67
B27: 6.03.01.02.02.01 - ALUGUEIS DE EQUIPAMENTOS | C27: BRASILSITE TELECOMUNICACOES LTDA. | E27: SERV. ALUGUEL EQUIPAMENTO 3.04 | F27: 46035 | G27: 46036 | H27: 919.75
B28: 6.03.01.02.02.01 - ALUGUEIS DE EQUIPAMENTOS | C28: BRASILSITE TELECOMUNICACOES LTDA. | E28: SERV. ALUGUEL EQUIPAMENTO 3.04 | F28: 46035 | G28: 46036 | H28: 1785.7
B29: 6.03.01.02.02.51 - INTERNET/COMUNICACOES | C29: BRASILSITE TELECOMUNICACOES LTDA. | E29: SERV. DE INTERNET 31.01 | F29: 46035 | G29: 46036 | H29: 149.73
B30: 6.03.01.02.02.51 - INTERNET/COMUNICACOES | C30: BRASILSITE TELECOMUNICACOES LTDA. | E30: SERV. DE INTERNET 31.01 | F30: 46035 | G30: 46036 | H30: 290.7
... B94: 6.03.01.02.02.77 - ASSESSORIA E SERVICO INFORMATICA | C94: BRFIBRA TELECOMUNICACOES LTDA | E94: PROCESSAMENTO DADOS 1.03 | F94: 46055 | G94: 46053 | H94: 1000
F95: TOTAL DO MÊS | H95: =SUM(H19:H94)
F97: SALDO DO BUDGET MENSAL | H97: =IF(H13=0,0,H13-H95)
F98: %BUDGET CONSUMIDO / MÊS | H98: =IF(H13=0,0,H95/H13)
F101: CONSUMO ACUMULADO ATUAL | H101: =H15+H95
F102: SALDO DO BUDGET ACUMULADO | H102: =H11-H101
F103: % BUDGET CONSUMIDO / ANO | H103: =IFERROR(H101/H11,0)
B106: Aprovador:
B107: Data:

Sheet Fevereiro
D1: ANÁLISE MENSAL BUDGET 2026
E4: ="Itapevi, "&TEXT(TODAY(),"dd ""de"" mmmm ""de"" aaaa")
B6: MÊS DE REFERÊNCIA | C6: Fev/2026
B7: RESPONSÁVEL | C7: Widson Rodrigues da Araujo - Gerente
B8: CENTRO DE CUSTO | C8: 25111001 - TI - DIVISAO DE NEGOCIO
G11: BUDGET/ANO | H11: 3329276.1
G13: BUDGET/MÊS | H13: 277235.16
F15: CONSUMO ACUMULADO ATÉ O MÊS ANTERIOR | H15: ='Janeiro'!H101
B17: CONTA CONTÁBIL | C17: FORNECEDOR | E17: DESCRIÇÃO | F17: DATA DE EMISSÃO | G17: DATA DE ENTREGA | H17: VALOR
B19: 6.03.01.02.02.31 - MANUTEN. SISTEMAS INFORMATICA | C19: IB SOFTWARE E SOLUCOES PARA LOGISTICA LTDA | E19: SERV. MANUT SISTEMA INFOR 1.07 | F19: 46055 | G19: 46055 | H19: 4635
B20: 6.03.01.02.02.51 - INTERNET/COMUNICACOES | C20: BRFIBRA TELECOMUNICACOES LTDA | E20: SERV. LINK INTERNET 01.04 | F20: 46055 | G20: 46055 | H20: 1000
B21: 6.03.01.02.02.51 - INTERNET/COMUNICACOES | C21: BRFIBRA TELECOMUNICACOES LTDA | E21: SERV. LINK INTERNET 01.04 | F21: 46055 | G21: 46055 | H21: 1000
B22: 6.03.01.02.02.51 - INTERNET/COMUNICACOES | C22: VOGEL SOLUCOES EM TELECOMUNICACOES E INFORMATICA S.A. | E22: SERV. LINK INTERNET 01.04 | F22: 46057 | G22: 46057 | H22: 856.03
B23: 6.03.01.02.02.51 - INTERNET/COMUNICACOES | C23: VOGEL SOLUCOES EM TELECOMUNICACOES E INFORMATICA S.A. | E23: SERV. LINK INTERNET 01.04 | F23: 46057 | G23: 46057 | H23: 1716.58
B24: 6.03.01.02.02.51 - INTERNET/COMUNICACOES | C24: VOGEL SOLUCOES EM TELECOMUNICACOES E INFORMATICA S.A. | E24: SERV. LINK INTERNET 01.04 | F24: 46057 | G24: 46057 | H24: 534.34
B25: 6.03.01.02.02.51 - INTERNET/COMUNICACOES | C25: WS-NET INTERNET E DADOS LTDA | E25: SERV. DE INTERNET 1.07 | F25: 46055 | G25: 46058 | H25: 577.4
B26: 6.03.01.02.02.51 - INTERNET/COMUNICACOES | C26: WS-NET INTERNET E DADOS LTDA | E26: SERV. DE INTERNET 1.07 | F26: 46055 | G26: 46058 | H26: 22.5
B27: 6.03.01.02.02.31 - MANUTEN. SISTEMAS INFORMATICA | C27: IB SOFTWARE E SOLUCOES PARA LOGISTICA LTDA | E27: SERV. MANUT SISTEMA INFOR 1.07 | F27: 46059 | G27: 46062 | H27: 4635
B28: 6.03.01.02.02.51 - INTERNET/COMUNICACOES | C28: DIRECT WIFI TELECOM LTDA | E28: SERV. LINK INTERNET 01.04 | F28: 46064 | G28: 46064 | H28: 600
B29: 6.03.01.02.02.31 - MANUTEN. SISTEMAS INFORMATICA | C29: E-MITH TECNOLOGIA E SERVICOS DE INFORMATICA EIRELI - EPP | E29: SERVICO LICENCA PROGRAMA 1.05 | F29: 46058 | G29: 46065 | H29: 43999.7
B30: 1.04.04.01.01.01 - CONSTR. EM ANDAMENTO | C30: DAYCOVAL LEASING - BANCO MULTIPLO S.A | E30: CONSTR. EM ANDAMENTO LEASING | F30: 46063 | G30: 46065 | H30: 10341.69
... B93: 6.03.01.02.02.51 - INTERNET/COMUNICACOES | C93: VOGEL SOLUCOES EM TELECOMUNICACOES E INFORMATICA S.A. | E93: SERV. LINK INTERNET 01.04 | F93: 46083 | G93: 46081 | H93: 252.67
F94: TOTAL DO MÊS | H94: =SUM(H19:H93)
F96: SALDO DO BUDGET MENSAL | H96: =IF(H13=0,0,H13-H94)
F97: %BUDGET CONSUMIDO / MÊS | H97: =IF(H13=0,0,H94/H13)
F100: CONSUMO ACUMULADO ATUAL | H100: =H15+H94
F101: SALDO DO BUDGET ACUMULADO | H101: =H11-H100
F102: % BUDGET CONSUMIDO / ANO | H102: =IFERROR(H100/H11,0)

Sheet Março
D1: ANÁLISE MENSAL BUDGET 2026
E4: ="Itapevi, "&TEXT(TODAY(),"dd ""de"" mmmm ""de"" aaaa")
B6: MÊS DE REFERÊNCIA | C6: Mar/2026
B7: RESPONSÁVEL | C7: Widson Rodrigues da Araujo - Gerente
B8: CENTRO DE CUSTO | C8: 25111001 - TI - DIVISAO DE NEGOCIO
G11: BUDGET/ANO | H11: 3329276.1
G13: BUDGET/MÊS | H13: 319235.16
F15: CONSUMO ACUMULADO ATÉ O MÊS ANTERIOR | H15: ='Fevereiro'!H100
B17: CONTA CONTÁBIL | C17: FORNECEDOR | E17: DESCRIÇÃO | F17: DATA DE EMISSÃO | G17: DATA DE ENTREGA | H17: VALOR
B19: 6.03.01.02.02.60 - MANUT. EQUP. INFORMATICA | C19: HELPY SERVICOS LTDA | E19: MONTAGEM/ASSIT TECNICA 14.01 | F19: 46090 | G19: 46090 | H19: 5455.51
B20: 6.03.01.02.02.60 - MANUT. EQUP. INFORMATICA | C20: HELPY SERVICOS LTDA | E20: MONTAGEM/ASSIT TECNICA 14.01 | F20: 46092 | G20: 46092 | H20: 5455.51
B21: 6.03.01.02.02.68 - BRINDES E DOACOES/INDEDUTIVEL | C21: NETWORK CONNECT BRASIL COMERCIOPRODUTOS ELETRONICOS LTDA EPP | E21: TV 50' | F21: 46093 | G21: 46093 | H21: 2699
B22: 6.03.01.02.02.13 - MANUTENCAO IMOBILIZADO | C22: APICE SISTEMAS DE ENERGIA LTDA | E22: SERVICO MANUTENCAO DE EQUIPAMENTO 14.01 | F22: 46094 | G22: 46094 | H22: 3450.12
B23: 6.03.01.02.02.31 - MANUTEN. SISTEMAS INFORMATICA | C23: AXWAY SOFTWARE DO BRASIL LTDA. | E23: SERV. MANUT SISTEMA INFOR 1.07 | F23: 46097 | G23: 46097 | H23: 7765.19
B24: 6.03.01.02.02.51 - INTERNET/COMUNICACOES | C24: RODOVIA SOLUCOES TECNOLOGICAS LTDA | E24: SUPORTE TECNICO T.I. 1.07 | F24: 46091 | G24: 46100 | H24: 2730.6
B25: 6.03.01.02.02.13 - MANUTENCAO IMOBILIZADO | C25: APICE SISTEMAS DE ENERGIA LTDA | E25: SERVICO MANUTENCAO DE EQUIPAMENTO 14.01 | F25: 46097 | G25: 46101 | H25: 3842.45
B26: 6.03.01.02.02.31 - MANUTEN. SISTEMAS INFORMATICA | C26: CURUPIRA S.A | E26: SERVICO LICENCA PROGRAMA 1.05 | F26: 46097 | G26: 46104 | H26: 7.11
B27: 6.03.01.02.02.31 - MANUTEN. SISTEMAS INFORMATICA | C27: CURUPIRA S.A | E27: SERVICO LICENCA PROGRAMA 1.05 | F27: 46097 | G27: 46104 | H27: 2981
B28: 6.03.01.02.02.31 - MANUTEN. SISTEMAS INFORMATICA | C28: INGRAM MICRO BRASIL LTDA | E28: SERVICO LICENCA PROGRAMA 1.05 | F28: 46097 | G28: 46104 | H28: 8291.44
B29: 6.03.01.02.02.51 - INTERNET/COMUNICACOES | C29: INGRAM MICRO BRASIL LTDA | E29: SUPORTE TECNICO T.I. 1.07 | F29: 46097 | G29: 46104 | H29: 1990.71
B30: 6.03.01.02.02.51 - INTERNET/COMUNICACOES | C30: VOGEL SOLUCOES EM TELECOMUNICACOES E INFORMATICA S.A. | E30: SERV. LINK INTERNET 01.04 | F30: 46097 | G30: 46104 | H30: 475.84
... B74: 6.03.01.02.02.77 - ASSESSORIA E SERVICO INFORMATICA | C74: BRFIBRA TELECOMUNICACOES LTDA | E74: PROCESSAMENTO DADOS 1.03 | F74: 46112 | G74: 46112 | H74: 900
F75: TOTAL DO MÊS | H75: =SUM(H19:H74)
F77: SALDO DO BUDGET MENSAL | H77: =IF(H13=0,0,H13-H75)
F78: %BUDGET CONSUMIDO / MÊS | H78: =IF(H13=0,0,H75/H13)
F81: CONSUMO ACUMULADO ATUAL | H81: =H15+H75
F82: SALDO DO BUDGET ACUMULADO | H82: =H11-H81
F83: % BUDGET CONSUMIDO / ANO | H83: =IFERROR(H81/H11,0)

Sheet Abril
D1: ANÁLISE MENSAL BUDGET 2026
E4: ="Itapevi, "&TEXT(TODAY(),"dd ""de"" mmmm ""de"" aaaa")
B6: MÊS DE REFERÊNCIA | C6: Abr/2026
B7: RESPONSÁVEL | C7: Widson Rodrigues da Araujo - Gerente
B8: CENTRO DE CUSTO | C8: 25111001 - TI - DIVISAO DE NEGOCIO
G11: BUDGET/ANO | H11: 3329276.1
G13: BUDGET/MÊS | H13: 373337.74
F15: CONSUMO ACUMULADO ATÉ O MÊS ANTERIOR | H15: ='Março'!H81
B17: CONTA CONTÁBIL | C17: FORNECEDOR | E17: DESCRIÇÃO | F17: DATA DE EMISSÃO | G17: DATA DE ENTREGA | H17: VALOR
B19: 6.03.01.02.02.60 - MANUT. EQUP. INFORMATICA | C19: SMART SISTEMAS DE ENERGIA LTDA | E19: MONTAGEM/ASSIT TECNICA 14.01 | F19: 46114 | G19: 46114 | H19: 986.67
B20: 6.03.01.02.02.51 - INTERNET/COMUNICACOES | C20: ALLREDE TELECOM LTDA | E20: SERV. DE INTERNET 1.07 | F20: 46119 | G20: 46119 | H20: 205.54
B21: 6.03.01.02.02.51 - INTERNET/COMUNICACOES | C21: ALLREDE TELECOM LTDA | E21: SERV. DE INTERNET 1.07 | F21: 46119 | G21: 46119 | H21: 205.54
B22: 6.03.01.02.02.51 - INTERNET/COMUNICACOES | C22: ALLREDE TELECOM LTDA | E22: SERV. DE INTERNET 1.07 | F22: 46119 | G22: 46119 | H22: 143.36
B23: 6.03.01.02.02.51 - INTERNET/COMUNICACOES | C23: ALLREDE TELECOM LTDA | E23: SERV. DE INTERNET 1.07 | F23: 46119 | G23: 46119 | H23: 205.54
B24: 6.03.01.02.02.51 - INTERNET/COMUNICACOES | C24: ALLREDE TELECOM LTDA | E24: SERV. DE INTERNET 1.07 | F24: 46119 | G24: 46119 | H24: 143.36
B25: 6.03.01.02.02.51 - INTERNET/COMUNICACOES | C25: ALLREDE TELECOM LTDA | E25: SERV. DE INTERNET 1.07 | F25: 46119 | G25: 46119 | H25: 205.54
B26: 6.03.01.02.02.51 - INTERNET/COMUNICACOES | C26: ALLREDE TELECOM LTDA | E26: SERV. DE INTERNET 1.07 | F26: 46119 | G26: 46119 | H26: 143.36
B27: 6.03.01.02.02.51 - INTERNET/COMUNICACOES | C27: ALLREDE TELECOM LTDA | E27: SERV. DE INTERNET 1.07 | F27: 46119 | G27: 46119 | H27: 143.36
B28: 6.03.01.02.02.51 - INTERNET/COMUNICACOES | C28: WS-NET INTERNET E DADOS LTDA | E28: SERV. DE INTERNET 1.07 | F28: 46114 | G28: 46120 | H28: 22.5
B29: 6.03.01.02.02.51 - INTERNET/COMUNICACOES | C29: WS-NET INTERNET E DADOS LTDA | E29: SERV. DE INTERNET 1.07 | F29: 46114 | G29: 46120 | H29: 577.4
B30: 6.03.01.02.02.51 - INTERNET/COMUNICACOES | C30: DIRECT WIFI TELECOM LTDA | E30: SERV. LINK INTERNET 01.04 | F30: 46118 | G30: 46120 | H30: 420
... B35: 6.03.01.02.02.51 - INTERNET/COMUNICACOES | C35: RODOVIA SOLUCOES TECNOLOGICAS LTDA | E35: SUPORTE TECNICO T.I. 1.07 | F35: 46121 | G35: 46121 | H35: 2693.7
F36: TOTAL DO MÊS | H36: =SUM(H19:H35)
F38: SALDO DO BUDGET MENSAL | H38: =IF(H13=0,0,H13-H36)
F39: %BUDGET CONSUMIDO / MÊS | H39: =IF(H13=0,0,H36/H13)
F42: CONSUMO ACUMULADO ATUAL | H42: =H15+H36
F43: SALDO DO BUDGET ACUMULADO | H43: =H11-H42
F44: % BUDGET CONSUMIDO / ANO | H44: =IFERROR(H42/H11,0)

Sheet Maio
D1: ANÁLISE MENSAL BUDGET 2026
E4: ="Itapevi, "&TEXT(TODAY(),"dd ""de"" mmmm ""de"" aaaa")
B6: MÊS DE REFERÊNCIA | C6: Mai/2026
B7: RESPONSÁVEL | C7: Widson Rodrigues da Araujo - Gerente
B8: CENTRO DE CUSTO | C8: 25111001 - TI - DIVISAO DE NEGOCIO
G11: BUDGET/ANO | H11: 3329276.1
G13: BUDGET/MÊS | H13: 365340.88
F15: CONSUMO ACUMULADO ATÉ O MÊS ANTERIOR | H15: ='Abril'!H42
B17: CONTA CONTÁBIL | C17: FORNECEDOR | E17: DESCRIÇÃO | F17: DATA DE EMISSÃO | G17: DATA DE ENTREGA | H17: VALOR
F28: TOTAL DO MÊS | H28: =SUM(H19:H27)
F30: SALDO DO BUDGET MENSAL | H30: =IF(H13=0,0,H13-H28)
F31: %BUDGET CONSUMIDO / MÊS | H31: =IF(H13=0,0,H28/H13)
F34: CONSUMO ACUMULADO ATUAL | H34: =H15+H28
F35: SALDO DO BUDGET ACUMULADO | H35: =H11-H34
F36: % BUDGET CONSUMIDO / ANO | H36: =IFERROR(H34/H11,0)

Sheet Junho
D1: ANÁLISE MENSAL BUDGET 2026
E4: ="Itapevi, "&TEXT(TODAY(),"dd ""de"" mmmm ""de"" aaaa")
B6: MÊS DE REFERÊNCIA | C6: Jun/2026
B7: RESPONSÁVEL | C7: Widson Rodrigues da Araujo - Gerente
B8: CENTRO DE CUSTO | C8: 25111001 - TI - DIVISAO DE NEGOCIO
G11: BUDGET/ANO | H11: 3329276.1
G13: BUDGET/MÊS | H13: 273367.88
F15: CONSUMO ACUMULADO ATÉ O MÊS ANTERIOR | H15: ='Maio'!H34
B17: CONTA CONTÁBIL | C17: FORNECEDOR | E17: DESCRIÇÃO | F17: DATA DE EMISSÃO | G17: DATA DE ENTREGA | H17: VALOR
F28: TOTAL DO MÊS | H28: =SUM(H19:H27)
F30: SALDO DO BUDGET MENSAL | H30: =IF(H13=0,0,H13-H28)
F31: %BUDGET CONSUMIDO / MÊS | H31: =IF(H13=0,0,H28/H13)
F34: CONSUMO ACUMULADO ATUAL | H34: =H15+H28
F35: SALDO DO BUDGET ACUMULADO | H35: =H11-H34
F36: % BUDGET CONSUMIDO / ANO | H36: =IFERROR(H34/H11,0)

Sheet Julho
D1: ANÁLISE MENSAL BUDGET 2026
E4: ="Itapevi, "&TEXT(TODAY(),"dd ""de"" mmmm ""de"" aaaa")
B6: MÊS DE REFERÊNCIA | C6: Jul/2026
B7: RESPONSÁVEL | C7: Widson Rodrigues da Araujo - Gerente
B8: CENTRO DE CUSTO | C8: 25111001 - TI - DIVISAO DE NEGOCIO
G11: BUDGET/ANO | H11: 3329276.1
G13: BUDGET/MÊS | H13: 270710.94
F15: CONSUMO ACUMULADO ATÉ O MÊS ANTERIOR | H15: ='Junho'!H34
B17: CONTA CONTÁBIL | C17: FORNECEDOR | E17: DESCRIÇÃO | F17: DATA DE EMISSÃO | G17: DATA DE ENTREGA | H17: VALOR
F28: TOTAL DO MÊS | H28: =SUM(H19:H27)
F30: SALDO DO BUDGET MENSAL | H30: =IF(H13=0,0,H13-H28)
F31: %BUDGET CONSUMIDO / MÊS | H31: =IF(H13=0,0,H28/H13)
F34: CONSUMO ACUMULADO ATUAL | H34: =H15+H28
F35: SALDO DO BUDGET ACUMULADO | H35: =H11-H34
F36: % BUDGET CONSUMIDO / ANO | H36: =IFERROR(H34/H11,0)

Sheet Agosto
D1: ANÁLISE MENSAL BUDGET 2026
E4: ="Itapevi, "&TEXT(TODAY(),"dd ""de"" mmmm ""de"" aaaa")
B6: MÊS DE REFERÊNCIA | C6: Ago/2026
B7: RESPONSÁVEL | C7: Widson Rodrigues da Araujo - Gerente
B8: CENTRO DE CUSTO | C8: 25111001 - TI - DIVISAO DE NEGOCIO
G11: BUDGET/ANO | H11: 3329276.1
G13: BUDGET/MÊS | H13: 248791.45
F15: CONSUMO ACUMULADO ATÉ O MÊS ANTERIOR | H15: ='Julho'!H34
B17: CONTA CONTÁBIL | C17: FORNECEDOR | E17: DESCRIÇÃO | F17: DATA DE EMISSÃO | G17: DATA DE ENTREGA | H17: VALOR
F28: TOTAL DO MÊS | H28: =SUM(H19:H27)
F30: SALDO DO BUDGET MENSAL | H30: =IF(H13=0,0,H13-H28)
F31: %BUDGET CONSUMIDO / MÊS | H31: =IF(H13=0,0,H28/H13)
F34: CONSUMO ACUMULADO ATUAL | H34: =H15+H28
F35: SALDO DO BUDGET ACUMULADO | H35: =H11-H34
F36: % BUDGET CONSUMIDO / ANO | H36: =IFERROR(H34/H11,0)

Sheet Setembro
D1: ANÁLISE MENSAL BUDGET 2026
E4: ="Itapevi, "&TEXT(TODAY(),"dd ""de"" mmmm ""de"" aaaa")
B6: MÊS DE REFERÊNCIA | C6: Set/2026
B7: RESPONSÁVEL | C7: Widson Rodrigues da Araujo - Gerente
B8: CENTRO DE CUSTO | C8: 25111001 - TI - DIVISAO DE NEGOCIO
G11: BUDGET/ANO | H11: 3329276.1
G13: BUDGET/MÊS | H13: 245809.15
F15: CONSUMO ACUMULADO ATÉ O MÊS ANTERIOR | H15: ='Agosto'!H34
B17: CONTA CONTÁBIL | C17: FORNECEDOR | E17: DESCRIÇÃO | F17: DATA DE EMISSÃO | G17: DATA DE ENTREGA | H17: VALOR
F28: TOTAL DO MÊS | H28: =SUM(H19:H27)
F30: SALDO DO BUDGET MENSAL | H30: =IF(H13=0,0,H13-H28)
F31: %BUDGET CONSUMIDO / MÊS | H31: =IF(H13=0,0,H28/H13)
F34: CONSUMO ACUMULADO ATUAL | H34: =H15+H28
F35: SALDO DO BUDGET ACUMULADO | H35: =H11-H34
F36: % BUDGET CONSUMIDO / ANO | H36: =IFERROR(H34/H11,0)

Sheet Outubro
D1: ANÁLISE MENSAL BUDGET 2026
E4: ="Itapevi, "&TEXT(TODAY(),"dd ""de"" mmmm ""de"" aaaa")
B6: MÊS DE REFERÊNCIA | C6: Out/2026
B7: RESPONSÁVEL | C7: Widson Rodrigues da Araujo - Gerente
B8: CENTRO DE CUSTO | C8: 25111001 - TI - DIVISAO DE NEGOCIO
G11: BUDGET/ANO | H11: 3329276.1
G13: BUDGET/MÊS | H13: 248832.45
F15: CONSUMO ACUMULADO ATÉ O MÊS ANTERIOR | H15: ='Setembro'!H34
B17: CONTA CONTÁBIL | C17: FORNECEDOR | E17: DESCRIÇÃO | F17: DATA DE EMISSÃO | G17: DATA DE ENTREGA | H17: VALOR
F28: TOTAL DO MÊS | H28: =SUM(H19:H27)
F30: SALDO DO BUDGET MENSAL | H30: =IF(H13=0,0,H13-H28)
F31: %BUDGET CONSUMIDO / MÊS | H31: =IF(H13=0,0,H28/H13)
F34: CONSUMO ACUMULADO ATUAL | H34: =H15+H28
F35: SALDO DO BUDGET ACUMULADO | H35: =H11-H34
F36: % BUDGET CONSUMIDO / ANO | H36: =IFERROR(H34/H11,0)

Sheet Novembro
D1: ANÁLISE MENSAL BUDGET 2026
E4: ="Itapevi, "&TEXT(TODAY(),"dd ""de"" mmmm ""de"" aaaa")
B6: MÊS DE REFERÊNCIA | C6: Nov/2026
B7: RESPONSÁVEL | C7: Widson Rodrigues da Araujo - Gerente
B8: CENTRO DE CUSTO | C8: 25111001 - TI - DIVISAO DE NEGOCIO
G11: BUDGET/ANO | H11: 3329276.1
G13: BUDGET/MÊS | H13: 216899.75
F15: CONSUMO ACUMULADO ATÉ O MÊS ANTERIOR | H15: ='Outubro'!H34
B17: CONTA CONTÁBIL | C17: FORNECEDOR | E17: DESCRIÇÃO | F17: DATA DE EMISSÃO | G17: DATA DE ENTREGA | H17: VALOR
F28: TOTAL DO MÊS | H28: =SUM(H19:H27)
F30: SALDO DO BUDGET MENSAL | H30: =IF(H13=0,0,H13-H28)
F31: %BUDGET CONSUMIDO / MÊS | H31: =IF(H13=0,0,H28/H13)
F34: CONSUMO ACUMULADO ATUAL | H34: =H15+H28
F35: SALDO DO BUDGET ACUMULADO | H35: =H11-H34
F36: % BUDGET CONSUMIDO / ANO | H36: =IFERROR(H34/H11,0)

Sheet Dezembro
D1: ANÁLISE MENSAL BUDGET 2026
E4: ="Itapevi, "&TEXT(TODAY(),"dd ""de"" mmmm ""de"" aaaa")
B6: MÊS DE REFERÊNCIA | C6: Dez/2026
B7: RESPONSÁVEL | C7: Widson Rodrigues da Araujo - Gerente
B8: CENTRO DE CUSTO | C8: 25111001 - TI - DIVISAO DE NEGOCIO
G11: BUDGET/ANO | H11: 3329276.1
G13: BUDGET/MÊS | H13: 220867.74
F15: CONSUMO ACUMULADO ATÉ O MÊS ANTERIOR | H15: ='Novembro'!H34
B17: CONTA CONTÁBIL | C17: FORNECEDOR | E17: DESCRIÇÃO | F17: DATA DE EMISSÃO | G17: DATA DE ENTREGA | H17: VALOR
F28: TOTAL DO MÊS | H28: =SUM(H19:H27)
F30: SALDO DO BUDGET MENSAL | H30: =IF(H13=0,0,H13-H28)
F31: %BUDGET CONSUMIDO / MÊS | H31: =IF(H13=0,0,H28/H13)
F34: CONSUMO ACUMULADO ATUAL | H34: =H15+H28
F35: SALDO DO BUDGET ACUMULADO | H35: =H11-H34
F36: % BUDGET CONSUMIDO / ANO | H36: =IFERROR(H34/H11,0)
